ByRequests/ByRequests.py
ByRequests/UserAgents.py
ByRequests/__init__.py
ByRequests-1.1.5.dist-info/METADATA
ByRequests-1.1.5.dist-info/RECORD
ByRequests-1.1.5.dist-info/WHEEL
ByRequests-1.1.5.dist-info/top_level.txt
