Metadata-Version: 2.1
Name: ByRequests
Version: 1.1.5
Summary: Helper to use proxy services with Requests
Home-page: https://github.com/Krakkev/ByRequests
Author: Kevin B. Garcia Alonso
Author-email: kevangy@hotmail.com
License: UNKNOWN
Download-URL: https://github.com/Krakkev/ByRequests/tarball/1.1.5
Keywords: requests,request,proxy,proxies,beautifulsoap,xpath,GET,POST
Platform: UNKNOWN
Classifier: Programming Language :: Python :: 3
Classifier: License :: OSI Approved :: MIT License
Requires-Dist: beautifulsoup4 (>=4.6.0)
Requires-Dist: bs4 (>=0.0.1)
Requires-Dist: requests (>=2.18.0)
Requires-Dist: urllib3 (>=1.21.1)
Requires-Dist: fake-useragent (>=0.1.11)
Requires-Dist: lxml (>=4.1.0)
Requires-Dist: eventlet (==0.23.0)
